{
	"instances": [
		{
			"id": 1,
			"cls": 2,
			"crop_rect": [
				[
					83,
					269
				],
				[
					487,
					593
				]
			],
			"roi_rect": [
				[
					115,
					301
				],
				[
					455,
					561
				]
			]
		},
		{
			"id": 2,
			"cls": 2,
			"crop_rect": [
				[
					595,
					296
				],
				[
					861,
					520
				]
			],
			"roi_rect": [
				[
					627,
					328
				],
				[
					829,
					488
				]
			]
		},
		{
			"id": 3,
			"cls": 2,
			"crop_rect": [
				[
					789,
					252
				],
				[
					1158,
					536
				]
			],
			"roi_rect": [
				[
					821,
					284
				],
				[
					1126,
					504
				]
			]
		}
	]
}